more_tk/src/more_tk/__init__.py
more_tk/tests/__init__.py
more_tk-0.1.3.dist-info/METADATA
more_tk-0.1.3.dist-info/WHEEL
more_tk-0.1.3.dist-info/RECORD
