Metadata-Version: 2.3
Name: more-tk
Version: 0.1.3
Summary: A project made to replicate tkinter but with different commands.
Author: Olivier Corbeil
Author-email: olicorb2000@gmail.com
Requires-Python: >=3.12
Classifier: Programming Language :: Python :: 3
Classifier: Programming Language :: Python :: 3.12
Classifier: Programming Language :: Python :: 3.13
